llama_index/postprocessor/voyageai_rerank/__init__.py
llama_index/postprocessor/voyageai_rerank/base.py
llama_index_postprocessor_voyageai_rerank-0.4.1.dist-info/METADATA
llama_index_postprocessor_voyageai_rerank-0.4.1.dist-info/WHEEL
llama_index_postprocessor_voyageai_rerank-0.4.1.dist-info/licenses/LICENSE
llama_index_postprocessor_voyageai_rerank-0.4.1.dist-info/RECORD
