Metadata-Version: 2.4
Name: llama-index-postprocessor-voyageai-rerank
Version: 0.4.1
Summary: llama-index postprocessor voyageai-rerank integration
Author-email: Your Name <you@example.com>
License-Expression: MIT
License-File: LICENSE
Requires-Python: <4.0,>=3.9
Requires-Dist: llama-index-core<0.15,>=0.13.0
Requires-Dist: voyageai<0.4.0,>=0.3.2; python_version >= '3.9' and python_version < '3.13'
